argus_ticket_rt.py
argus_ticket_rt-1.2.0.dist-info/licenses/LICENSE
argus_ticket_rt-1.2.0.dist-info/WHEEL
argus_ticket_rt-1.2.0.dist-info/METADATA
argus_ticket_rt-1.2.0.dist-info/RECORD
