Metadata-Version: 2.4
Name: argus_ticket_rt
Version: 1.2.0
Summary: Allow argus-server to create tickets in Request Tracker
Author-email: Johanna England <johanna.england@sikt.no>
Maintainer-email: Johanna England <johanna.england@sikt.no>
Requires-Python: >=3.10
Classifier: Framework :: Django
Classifier: Framework :: Django :: 4.2
Classifier: Framework :: Django :: 5.1
Classifier: Framework :: Django :: 5.2
Classifier: Intended Audience :: Information Technology
Classifier: Intended Audience :: System Administrators
Classifier: License :: OSI Approved :: GNU General Public License v3 or later (GPLv3+)
Classifier: Programming Language :: Python :: 3 :: Only
Classifier: Programming Language :: Python :: 3.10
Classifier: Programming Language :: Python :: 3.11
Classifier: Programming Language :: Python :: 3.12
Classifier: Programming Language :: Python :: 3.13
Classifier: Topic :: System :: Monitoring
License-File: LICENSE
Requires-Dist: argus-server>=1.34.0
Requires-Dist: rt>=3.3.6
Requires-Dist: tox ; extra == "test"
Requires-Dist: coverage ; extra == "test"
Project-URL: Home, https://github.com/Uninett/argus_ticket_rt
Project-URL: Issues, https://github.com/Uninett/argus_ticket_rt/issues
Provides-Extra: test
